universal_mcp_apollo/README.md
universal_mcp_apollo/__init__.py
universal_mcp_apollo/app.py
universal_mcp_apollo/server.py
universal_mcp_apollo-0.1.10.dist-info/METADATA
universal_mcp_apollo-0.1.10.dist-info/WHEEL
universal_mcp_apollo-0.1.10.dist-info/entry_points.txt
universal_mcp_apollo-0.1.10.dist-info/licenses/LICENSE
universal_mcp_apollo-0.1.10.dist-info/RECORD
